seqq/__init__.py
seqq/api_client.py
seqq/api_response.py
seqq/configuration.py
seqq/exceptions.py
seqq/py.typed
seqq/rest.py
seqq/api/__init__.py
seqq/api/seqq_service_api.py
seqq/models/__init__.py
seqq/models/apiv1alpha_list_records_response.py
seqq/models/apiv1alpha_search.py
seqq/models/blastn_task.py
seqq/models/options_matrix.py
seqq/models/options_strand.py
seqq/models/options_task.py
seqq/models/protobuf_any.py
seqq/models/rpc_status.py
seqq/models/search_program.py
seqq/models/search_state.py
seqq/models/seqq_service_batch_create_records_request.py
seqq/models/seqq_service_batch_create_sequences_request.py
seqq/models/seqq_service_batch_start_searches_request.py
seqq/models/the_integration_to_update.py
seqq/models/v1alpha_alignment.py
seqq/models/v1alpha_batch_create_records_response.py
seqq/models/v1alpha_batch_create_sequences_response.py
seqq/models/v1alpha_batch_start_searches_response.py
seqq/models/v1alpha_blastn.py
seqq/models/v1alpha_code.py
seqq/models/v1alpha_collection.py
seqq/models/v1alpha_create_record_request.py
seqq/models/v1alpha_create_records_from_file_response.py
seqq/models/v1alpha_create_sequence_request.py
seqq/models/v1alpha_create_sequences_from_file_response.py
seqq/models/v1alpha_file_encoding.py
seqq/models/v1alpha_hit.py
seqq/models/v1alpha_integration.py
seqq/models/v1alpha_integration_google_drive.py
seqq/models/v1alpha_integration_ncbi.py
seqq/models/v1alpha_list_collections_response.py
seqq/models/v1alpha_list_integrations_response.py
seqq/models/v1alpha_list_records_response.py
seqq/models/v1alpha_list_searches_response.py
seqq/models/v1alpha_list_sequences_response.py
seqq/models/v1alpha_options.py
seqq/models/v1alpha_record.py
seqq/models/v1alpha_search.py
seqq/models/v1alpha_sequence.py
seqq/models/v1alpha_start_search_request.py
seqq/models/v1alpha_strategy.py
seqq-0.0.49.dist-info/METADATA
seqq-0.0.49.dist-info/WHEEL
seqq-0.0.49.dist-info/top_level.txt
seqq-0.0.49.dist-info/RECORD
