Metadata-Version: 2.1
Name: seqq
Version: 0.0.49
Summary: seqq
Home-page: https://github.com/jjti/seqq-python
Author: OpenAPI Generator community
Author-email: team@openapitools.org
Keywords: OpenAPI,OpenAPI-Generator,seqq
Requires-Dist: urllib3 <2.1.0,>=1.25.3
Requires-Dist: python-dateutil
Requires-Dist: pydantic >=2
Requires-Dist: typing-extensions >=4.7.1
